material/__init__.py
material/apps.py
material/admin/__init__.py
material/admin/apps.py
material/admin/options.py
material/admin/settings.py
material/admin/sites.py
material/admin/urls.py
material/admin/views.py
material/admin/widgets.py
material/locale/es/LC_MESSAGES/django.mo
material/locale/es/LC_MESSAGES/django.po
material/locale/es_AR/LC_MESSAGES/django.mo
material/locale/es_AR/LC_MESSAGES/django.po
material/locale/ru/LC_MESSAGES/django.mo
material/locale/ru/LC_MESSAGES/django.po
material/locale/uk/LC_MESSAGES/django.mo
material/locale/uk/LC_MESSAGES/django.po
material/locale/zh_Hans/LC_MESSAGES/django.mo
material/locale/zh_Hans/LC_MESSAGES/django.po
material/static/admin/js/SelectFilter2.js
material/static/admin/js/inlines.js
material/static/admin/js/inlines.min.js
material/static/admin/js/prepopulate.js
material/static/material/admin/css/additional_submit_line.min.css
material/static/material/admin/css/admin-out-black.min.css
material/static/material/admin/css/admin-out-green.min.css
material/static/material/admin/css/admin-out-night.min.css
material/static/material/admin/css/admin-out-red.min.css
material/static/material/admin/css/admin-out.min.css
material/static/material/admin/css/app_content.min.css
material/static/material/admin/css/autocomplete.min.css
material/static/material/admin/css/base_site-black.min.css
material/static/material/admin/css/base_site-green.min.css
material/static/material/admin/css/base_site-night.min.css
material/static/material/admin/css/base_site-red.min.css
material/static/material/admin/css/base_site-responsive.min.css
material/static/material/admin/css/base_site-theme.min.css
material/static/material/admin/css/base_site.min.css
material/static/material/admin/css/change_form.min.css
material/static/material/admin/css/changelists.min.css
material/static/material/admin/css/clearable_file_input.min.css
material/static/material/admin/css/date-input.min.css
material/static/material/admin/css/header.min.css
django_material_admin-1.8.6.dist-info/METADATA
django_material_admin-1.8.6.dist-info/WHEEL
django_material_admin-1.8.6.dist-info/top_level.txt
django_material_admin-1.8.6.dist-info/RECORD
