Metadata-Version: 2.1
Name: django-material-admin
Version: 1.8.6
Summary: Material Design For Django Administration
Home-page: https://github.com/MaistrenkoAnton/django-material-admin
Author: Anton Maistrenko
Author-email: it2015maistrenko@gmail.com
License: MIT License
Platform: UNKNOWN
Classifier: Programming Language :: Python :: 3.6
Classifier: Programming Language :: Python :: 3.7
Classifier: Programming Language :: Python :: 3.8
Classifier: Framework :: Django :: 3.2
Classifier: License :: OSI Approved :: MIT License
Classifier: Operating System :: OS Independent
